x_segment_anything/__init__.py
x_segment_anything/automatic_mask_generator.py
x_segment_anything/build_sam.py
x_segment_anything/predictor.py
x_segment_anything/modeling/__init__.py
x_segment_anything/modeling/common.py
x_segment_anything/modeling/image_encoder.py
x_segment_anything/modeling/mask_decoder.py
x_segment_anything/modeling/mask_decoder_coralscop.py
x_segment_anything/modeling/prompt_encoder.py
x_segment_anything/modeling/rep_vit.py
x_segment_anything/modeling/repvit.py
x_segment_anything/modeling/sam.py
x_segment_anything/modeling/tiny_vit_sam.py
x_segment_anything/modeling/transformer.py
x_segment_anything/utils/__init__.py
x_segment_anything/utils/amg.py
x_segment_anything/utils/transforms.py
x_segment_anything-0.0.8.dist-info/LICENSE
x_segment_anything-0.0.8.dist-info/METADATA
x_segment_anything-0.0.8.dist-info/WHEEL
x_segment_anything-0.0.8.dist-info/top_level.txt
x_segment_anything-0.0.8.dist-info/RECORD
