Metadata-Version: 2.1
Name: x_segment_anything
Version: 0.0.8
Summary: Segment Anything Model (SAM) modules combined in the same API (to make life easier).
Author-email: Jordan Pierce <jordan.pierce@noaa.gov>
License: MIT License
Project-URL: Homepage, https://github.com/Jordan-Pierce/xSAM
Keywords: xSAM
Classifier: Intended Audience :: Developers
Classifier: License :: OSI Approved :: MIT License
Classifier: Natural Language :: English
Classifier: Programming Language :: Python :: 3.8
Classifier: Programming Language :: Python :: 3.9
Classifier: Programming Language :: Python :: 3.10
Classifier: Programming Language :: Python :: 3.11
Classifier: Programming Language :: Python :: 3.12
Requires-Python: >=3.8
License-File: LICENSE
Requires-Dist: torch
Requires-Dist: torchvision
Requires-Dist: timm
Requires-Dist: numpy
Provides-Extra: all
Requires-Dist: matplotlib; extra == "all"
Requires-Dist: pycocotools; extra == "all"
Requires-Dist: opencv-python; extra == "all"
Requires-Dist: onnx; extra == "all"
Requires-Dist: onnxruntime; extra == "all"
Provides-Extra: dev
Requires-Dist: flake8; extra == "dev"
Requires-Dist: isort; extra == "dev"
Requires-Dist: black; extra == "dev"
Requires-Dist: mypy; extra == "dev"
